LICENSE.md
MANIFEST.in
README.rst
setup.cfg
setup.py
bin/make_ms
bin/night_length
bin/roboschedulerversion.py
cextern/Makefile
cextern/README.txt
cextern/cCadenceCore.cpp
cextern/cadenceCore.cpp
include/cadenceCore.h
python/roboscheduler/__init__.py
python/roboscheduler/cadence.py
python/roboscheduler/coords.py
python/roboscheduler/fields.py
python/roboscheduler/ks91.py
python/roboscheduler/moonphase.py
python/roboscheduler/observations.py
python/roboscheduler/scheduler.py
python/roboscheduler/sunpos2.py
python/roboscheduler/core/__init__.py
python/roboscheduler/core/exceptions.py
python/roboscheduler/etc/master_schedule_apo_gamma.par
python/roboscheduler/etc/master_schedule_apo_impossible.par
python/roboscheduler/etc/master_schedule_apo_maximal.par
python/roboscheduler/etc/master_schedule_apo_maximal_v2.par
python/roboscheduler/etc/master_schedule_apo_maximal_v3.par
python/roboscheduler/etc/master_schedule_apo_may21.par
python/roboscheduler/etc/master_schedule_apo_minimal.par
python/roboscheduler/etc/master_schedule_apo_normal.par
python/roboscheduler/etc/master_schedule_apo_normal_v2.par
python/roboscheduler/etc/master_schedule_apo_normal_v3.par
python/roboscheduler/etc/master_schedule_apo_normal_v4.par
python/roboscheduler/etc/master_schedule_apo_normal_v5.par
python/roboscheduler/etc/master_schedule_apo_plates.par
python/roboscheduler/etc/master_schedule_apo_test.par
python/roboscheduler/etc/master_schedule_apo_v6.par
python/roboscheduler/etc/master_schedule_apo_v6_alttwi.par
python/roboscheduler/etc/master_schedule_apo_v6_vartwi.par
python/roboscheduler/etc/master_schedule_lco_gamma.par
python/roboscheduler/etc/master_schedule_lco_impossible.par
python/roboscheduler/etc/master_schedule_lco_maximal.par
python/roboscheduler/etc/master_schedule_lco_maximal_v2.par
python/roboscheduler/etc/master_schedule_lco_maximal_v3.par
python/roboscheduler/etc/master_schedule_lco_may21.par
python/roboscheduler/etc/master_schedule_lco_minimal.par
python/sdss_roboscheduler.egg-info/PKG-INFO
python/sdss_roboscheduler.egg-info/SOURCES.txt
python/sdss_roboscheduler.egg-info/dependency_links.txt
python/sdss_roboscheduler.egg-info/not-zip-safe
python/sdss_roboscheduler.egg-info/requires.txt
python/sdss_roboscheduler.egg-info/top_level.txt
