Metadata-Version: 2.1
Name: sdss-roboscheduler
Version: 2.1.0
Summary: fps scheduling software for SDSS V
Home-page: https://github.com/sdss/roboscheduler
Author: Michael Blanton
Maintainer: John Donor
Maintainer-email: j.donor@tcu.edu
License: BSD 3-Clause License
Project-URL: Repository, https://github.com/sdss/roboscheduler
Keywords: astronomy,software
Classifier: Intended Audience :: Science/Research
Classifier: Natural Language :: English
Classifier: Operating System :: OS Independent
Classifier: Programming Language :: Python
Classifier: Programming Language :: Python :: 3.7
Classifier: Programming Language :: Python :: 3.8
Classifier: Programming Language :: Python :: 3.9
Classifier: Programming Language :: Python :: 3.10
Classifier: Topic :: Software Development :: Libraries :: Python Modules
Requires-Python: >=3.7
Provides-Extra: dev
License-File: LICENSE.md
